{
  "generatedAt": "2026-05-07T15:14:08.495Z",
  "total": 2,
  "modules": [
    {
      "id": "a7aad1d5-c185-4c8a-a618-3279b5a2ede2",
      "slug": "html-dasar-wpu",
      "title": "🚀 HTML Dasar Untuk Pemula - WPU",
      "description": "Modul ini adalah sebuah kurikulum belajar mandiri yang disusun untuk membantu Anda menguasai fondasi utama pengembangan web. Kami mengadaptasi materi pembelajaran dari seri video legendaris milik Sandhika Galih (Web Programming UNPAS) dan merestrukturnya ke dalam format yang lebih interaktif.",
      "lessonCount": 22,
      "image": null,
      "path": "content/modules/html-dasar-wpu.json"
    },
    {
      "id": "2738d2f5-4f7a-4c8a-9d62-8279b5a2ede2",
      "slug": "python-dasar-halotech",
      "title": "🐍 Belajar Python Bahasa Indonesia - HaloTech",
      "description": "Kurikulum belajar mandiri yang disusun oleh PRC Academy berdasarkan seri kursus HaloTech Academy. Modul ini dirancang untuk membimbing Anda belajar Python dari nol hingga mahir dengan alur yang sistematis, kuis interaktif, dan tantangan praktik langsung.\n\nPlatform & Kurikulum: Raja Capybara Academy\nSumber Materi: HaloTech Academy",
      "lessonCount": 19,
      "image": null,
      "path": "content/modules/python-dasar-halotech.json"
    }
  ]
}
